jami/__init__.py
jami/encryption.py
jami/main.py
logo.jpeg
jami_cli-0.7.0.dist-info/LICENSE
jami_cli-0.7.0.dist-info/METADATA
jami_cli-0.7.0.dist-info/WHEEL
jami_cli-0.7.0.dist-info/entry_points.txt
jami_cli-0.7.0.dist-info/RECORD
